{"d":{"actions":{"finish":[],"init":[],"start":[]},"adjustedMax":"","adjustedMin":"","alpha":1,"anchorFrameType":"SCREEN","anchorPoint":"CENTER","animation":{"finish":{"duration_type":"seconds","easeStrength":3,"easeType":"none","type":"none"},"main":{"duration_type":"seconds","easeStrength":3,"easeType":"none","type":"none"},"start":{"duration_type":"seconds","easeStrength":3,"easeType":"none","type":"none"}},"authorOptions":[],"color":[1,1,1,1],"conditions":[{"changes":[{"property":"color","value":[1,0.53333336114883,0.52941179275513,1]}],"check":{"value":0,"variable":"spellInRange"}}],"config":[],"cooldown":true,"cooldownEdge":false,"cooldownSwipe":true,"cooldownTextDisabled":true,"desaturate":false,"frameStrata":1,"height":48,"icon":true,"iconSource":-1,"id":"Target Slowed","information":[],"internalVersion":84,"inverse":false,"keepAspectRatio":false,"load":{"class":{"multi":[]},"size":{"multi":[]},"spec":{"multi":[]},"talent":{"multi":[]}},"progressSource":[-1,""],"regionType":"icon","selfPoint":"CENTER","subRegions":[{"type":"subbackground"},{"anchorXOffset":0,"anchorYOffset":0,"anchor_point":"CENTER","rotateText":"NONE","text_anchorYOffset":5,"text_automaticWidth":"Auto","text_color":[1,1,1,1],"text_fixedWidth":64,"text_font":"Friz Quadrata TT","text_fontSize":20,"text_fontType":"OUTLINE","text_justify":"CENTER","text_selfPoint":"AUTO","text_shadowColor":[0,0,0,1],"text_shadowXOffset":0,"text_shadowYOffset":0,"text_text":"%p","text_text_format_p_format":"timed","text_text_format_p_time_dynamic_threshold":60,"text_text_format_p_time_format":0,"text_text_format_p_time_legacy_floor":false,"text_text_format_p_time_mod_rate":true,"text_text_format_p_time_precision":1,"text_text_format_s_format":"none","text_visible":true,"text_wordWrap":"WordWrap","type":"subtext"},{"glow":false,"glowBorder":false,"glowColor":[1,1,1,1],"glowDuration":1,"glowFrequency":0.25,"glowLength":10,"glowLines":8,"glowScale":1,"glowThickness":1,"glowType":"buttonOverlay","glowXOffset":0,"glowYOffset":0,"type":"subglow","useGlowColor":false}],"tocversion":110105,"triggers":{"activeTriggerMode":-10,"disjunctive":"any","1":{"trigger":{"auranames":[],"auraspellids":["116","1715","2120","3409","3600","5116","6343","7992","12323","12486","12544","15407","31589","35346","44614","45524","50259","50433","51490","58180","61391","116095","118000","121253","123586","127797","135299","147732","157981","160065","160067","183218","185763","186387","195645","196840","198222","198813","201787","204263","204843","205021","205708","206930","208278","211793","212792","213405","228354","255937","257478","257777","258313","267899","268896","270499","271564","272834","273977","277953","279303","280184","280583","280604","288962","289308","289526","290366"],"debuffType":"HARMFUL","event":"Health","matchesShowOn":"showOnActive","names":[],"spellIds":[],"subeventPrefix":"SPELL","subeventSuffix":"_CAST_START","type":"aura2","unit":"target","useExactSpellId":true,"useName":false,"use_debuffClass":false},"untrigger":[]}},"uid":"zNA4AvK5luL","useAdjustededMax":false,"useAdjustededMin":false,"useCooldownModRate":true,"width":48,"xOffset":50,"yOffset":0,"zoom":0},"m":"d","s":"5.19.8","v":1421}
